panelapp/Panelapp.py
panelapp/__init__.py
panelapp/api.py
panelapp/queries.py
tests/__init__.py
tests/test_queries.py
panelapp-0.7.4.dist-info/LICENCE
panelapp-0.7.4.dist-info/METADATA
panelapp-0.7.4.dist-info/WHEEL
panelapp-0.7.4.dist-info/top_level.txt
panelapp-0.7.4.dist-info/RECORD
