Metadata-Version: 2.1
Name: panelapp
Version: 0.7.4
Summary: General purpose Panelapp package
Home-page: https://github.com/NHS-NGS/panelapp
Author: Yujin Kim
Author-email: yujin.kim@hotmail.fr
License: UNKNOWN
Platform: UNKNOWN
Classifier: Programming Language :: Python :: 3
Classifier: License :: OSI Approved :: MIT License
Classifier: Operating System :: OS Independent
Requires-Python: >=3.5
